sphinx_lfs_content
