Metadata-Version: 2.4
Name: sphinx_lfs_content
Version: 1.1.10
Summary: Ensure existence of LFS content in your LFS builds
Author: Dominic Kempf
Author-email: dominic.kempf@iwr.uni-heidelberg.de
Classifier: Framework :: Sphinx :: Extension
Classifier: Programming Language :: Python :: 3
Classifier: Operating System :: Unix
Classifier: License :: OSI Approved :: MIT License
License-File: LICENSE.md
Requires-Dist: requests
Dynamic: author
Dynamic: author-email
Dynamic: classifier
Dynamic: description
Dynamic: description-content-type
Dynamic: license-file
Dynamic: requires-dist
Dynamic: summary
